{"directed":false,"multigraph":false,"graph":{},"nodes":[{"id":"n1","label":"cup","type":0,"activation":0.0},{"id":"n2","label":"table","type":0,"activation":0.0},{"id":"n3","label":"red","type":2,"activation":0.0},{"id":"n4","label":"round","type":2,"activation":0.0},{"id":"n5","label":"cup_instance_1","type":1,"activation":0.0},{"id":"n6","label":"table_instance_1","type":1,"activation":0.0},{"id":"n7","label":"person","type":0,"activation":0.0},{"id":"n8","label":"hand","type":0,"activation":0.0},{"id":"n9","label":"grasp","type":0,"activation":0.0},{"id":"n10","label":"person_instance_1","type":1,"activation":0.0},{"id":"n11","label":"hand_instance_1","type":1,"activation":0.0},{"id":"n12","label":"concept_1","type":0,"activation":0.0},{"id":"n13","label":"concept_2","type":0,"activation":0.0},{"id":"n14","label":"concept_3","type":0,"activation":0.0},{"id":"n15","label":"concept_4","type":0,"activation":0.0}],"links":[{"source":"n5","target":"n1","tension":1.0,"relation":"INSTANCE_OF","weight":1.0},{"source":"n6","target":"n2","tension":1.0,"relation":"INSTANCE_OF","weight":1.0},{"source":"n5","target":"n3","tension":0.800000011920929,"relation":"OBSERVED_AS","weight":0.800000011920929},{"source":"n5","target":"n4","tension":0.8999999761581421,"relation":"OBSERVED_AS","weight":0.8999999761581421},{"source":"n5","target":"n6","tension":0.699999988079071,"relation":"NEAR","weight":0.699999988079071},{"source":"n5","target":"n6","tension":0.6000000238418579,"relation":"CO_OCCURS_WITH","weight":0.6000000238418579},{"source":"n10","target":"n7","tension":1.0,"relation":"INSTANCE_OF","weight":1.0},{"source":"n11","target":"n8","tension":1.0,"relation":"INSTANCE_OF","weight":1.0},{"source":"n11","target":"n10","tension":0.8999999761581421,"relation":"INSTANCE_OF","weight":0.8999999761581421},{"source":"n11","target":"n5","tension":0.800000011920929,"relation":"NEAR","weight":0.800000011920929},{"source":"n10","target":"n9","tension":0.699999988079071,"relation":"OBSERVED_AS","weight":0.699999988079071},{"source":"n12","target":"n8","tension":0.5,"relation":"CO_OCCURS_WITH","weight":0.5},{"source":"n13","target":"n10","tension":0.5,"relation":"CO_OCCURS_WITH","weight":0.5},{"source":"n14","target":"n7","tension":0.5,"relation":"CO_OCCURS_WITH","weight":0.5},{"source":"n15","target":"n12","tension":0.5,"relation":"CO_OCCURS_WITH","weight":0.5}]}